blender_stylesheet/__init__.py
blender_stylesheet/blender_stylesheet.qss
blender_stylesheet/images/QCheckBox_checked.png
blender_stylesheet/images/QCheckBox_unchecked.png
blender_stylesheet/images/QCheckbox_checked_hover.png
blender_stylesheet/images/QCheckbox_unchecked_hover.png
blender_stylesheet/images/QComboBox_down_arrow.png
blender_stylesheet/images/QRadioButton_checked.png
blender_stylesheet/images/QRadioButton_checked_hover.png
blender_stylesheet/images/QRadioButton_unchecked.png
blender_stylesheet/images/QRadioButton_unchecked_hover.png
blender_stylesheet/images/QSpinBox_down_arrow.png
blender_stylesheet/images/QSpinBox_up_arrow.png
blender_stylesheet/images/blender_icon_16.png
blender_qt_stylesheet-0.0.3.dist-info/LICENSE
blender_qt_stylesheet-0.0.3.dist-info/METADATA
blender_qt_stylesheet-0.0.3.dist-info/WHEEL
blender_qt_stylesheet-0.0.3.dist-info/top_level.txt
blender_qt_stylesheet-0.0.3.dist-info/RECORD
