Metadata-Version: 2.1
Name: blender-qt-stylesheet
Version: 0.0.3
Summary: style qt like Blender
Author: https://tech-artists.org/
License: Mozilla Public License Version 2.0
Project-URL: Homepage, https://github.com/hannesdelbeke/blender-qt-stylesheet
Keywords: blender,pyside,pyside2,pyside6,qt,dark,darkstyle,night,darkmode
Classifier: Programming Language :: Python :: 3.7
Requires-Python: >=3.4
License-File: LICENSE
Requires-Dist: qtpy
Requires-Dist: importlib-metadata ; python_version < "3.7"
